{
    "Ar36": {
        "error": 0.0001138810353797309,
        "filter_outliers_dict": {
            "filter_outliers": true,
            "iterations": 1,
            "std_devs": 2
        },
        "fit": "Parabolic",
        "fn": 577,
        "include_baseline_error": false,
        "n": 600,
        "reviewed": true,
        "value": 0.002240622293066212
    },
    "Ar37": {
        "error": 0.0066301171508182195,
        "filter_outliers_dict": {
            "filter_outliers": true,
            "iterations": 1,
            "std_devs": 2
        },
        "fit": "Parabolic",
        "fn": 578,
        "include_baseline_error": false,
        "n": 600,
        "reviewed": true,
        "value": 0.14612205806025327
    },
    "Ar38": {
        "error": 0.019999902906743087,
        "filter_outliers_dict": {
            "filter_outliers": true,
            "iterations": 1,
            "std_devs": 2
        },
        "fit": "Linear",
        "fn": 590,
        "include_baseline_error": false,
        "n": 600,
        "reviewed": true,
        "value": 0.2335154698232394
    },
    "Ar39": {
        "error": 0.004330838233578113,
        "filter_outliers_dict": {
            "filter_outliers": true,
            "iterations": 1,
            "std_devs": 2
        },
        "fit": "Linear",
        "fn": 569,
        "include_baseline_error": false,
        "n": 600,
        "reviewed": true,
        "value": 6.228345950718406
    },
    "Ar40": {
        "error": 0.011297404821456986,
        "filter_outliers_dict": {
            "filter_outliers": true,
            "iterations": 1,
            "std_devs": 2
        },
        "fit": "Parabolic",
        "fn": 575,
        "include_baseline_error": false,
        "n": 600,
        "reviewed": true,
        "value": 83.99749825414044
    },
    "Ar41": {
        "error": 0.12292392350180416,
        "fit": "average_SEM",
        "value": 0.16421457911390766
    }
}