{
    "Ar36": {
        "error": 0.0002552176700173642,
        "filter_outliers_dict": {
            "filter_outliers": true,
            "iterations": 1,
            "std_devs": 2
        },
        "fit": "Parabolic",
        "fn": 381,
        "include_baseline_error": false,
        "n": 400,
        "reviewed": true,
        "value": 0.015408892397662088
    },
    "Ar37": {
        "error": 0.0326782677770266,
        "filter_outliers_dict": {
            "filter_outliers": true,
            "iterations": 1,
            "std_devs": 2
        },
        "fit": "Parabolic",
        "fn": 380,
        "include_baseline_error": false,
        "n": 400,
        "reviewed": true,
        "value": 0.4522611551271567
    },
    "Ar38": {
        "error": 0.010326306005792017,
        "filter_outliers_dict": {
            "filter_outliers": true,
            "iterations": 1,
            "std_devs": 2
        },
        "fit": "Linear",
        "fn": 383,
        "include_baseline_error": false,
        "n": 400,
        "reviewed": true,
        "value": 0.14694670247814862
    },
    "Ar39": {
        "error": 0.005079584005349368,
        "filter_outliers_dict": {
            "filter_outliers": true,
            "iterations": 1,
            "std_devs": 2
        },
        "fit": "Linear",
        "fn": 382,
        "include_baseline_error": false,
        "n": 400,
        "reviewed": true,
        "value": 0.30091253269340545
    },
    "Ar40": {
        "error": 0.016163460115289737,
        "filter_outliers_dict": {
            "filter_outliers": true,
            "iterations": 1,
            "std_devs": 2
        },
        "fit": "Parabolic",
        "fn": 383,
        "include_baseline_error": false,
        "n": 400,
        "reviewed": true,
        "value": 4.8750105155110255
    },
    "Ar41": {
        "error": 0.11944961539737779,
        "fit": "average_SEM",
        "value": 0.14962914766627364
    }
}