{
    "Ar36": {
        "error": 0.0042327080052167298, 
        "fit": "parabolic", 
        "value": 0.10146925995994255
    }, 
    "Ar37": {
        "error": 0.25521356448852323, 
        "fit": "linear", 
        "value": 0.15919567083544242
    }, 
    "Ar38": {
        "error": 0.10833709217323381, 
        "fit": "linear", 
        "value": 0.42871686784894181
    }, 
    "Ar39": {
        "error": 0.062331350331103388, 
        "fit": "parabolic", 
        "value": 7.9863709779227197
    }, 
    "Ar40": {
        "error": 0.13513935952171782, 
        "fit": "parabolic", 
        "value": 36.210536841374335
    }, 
    "Ar41": {
        "error": 0.11753614337840991, 
        "fit": "average_SEM", 
        "value": -0.13828654831508175
    }
}