{
    "Ar36": {
        "error": 0.00099412649227201191, 
        "fit": "parabolic", 
        "value": 0.0031825489700912542
    }, 
    "Ar37": {
        "error": 0.24625809377706609, 
        "fit": "linear", 
        "value": 0.17920048273949035
    }, 
    "Ar38": {
        "error": 0.11213738094802284, 
        "fit": "linear", 
        "value": -0.097576051853158902
    }, 
    "Ar39": {
        "error": 0.059941036523573119, 
        "fit": "parabolic", 
        "value": 0.67417288525522978
    }, 
    "Ar40": {
        "error": 0.12126997895449831, 
        "fit": "parabolic", 
        "value": 1.0529545553587174
    }, 
    "Ar41": {
        "error": 0.11672781682929388, 
        "fit": "average_SEM", 
        "value": -0.10959633244408906
    }
}