{
    "AX": {
        "error": 0.004992012170726832,
        "filter_outliers_dict": {
            "filter_outliers": true,
            "iterations": 1,
            "std_devs": 2
        },
        "fit": "Average",
        "fn": 86,
        "include_baseline_error": false,
        "n": 90,
        "reviewed": true,
        "value": 0.15964578438636867
    },
    "CDD": {
        "error": 3.4591534493668015e-06,
        "filter_outliers_dict": {
            "filter_outliers": true,
            "iterations": 1,
            "std_devs": 10
        },
        "fit": "Average",
        "fn": 90,
        "include_baseline_error": false,
        "n": 90,
        "reviewed": true,
        "value": 7.037940667942166e-06
    },
    "H1": {
        "error": 0.004344252076534164,
        "filter_outliers_dict": {
            "filter_outliers": true,
            "iterations": 1,
            "std_devs": 2
        },
        "fit": "Average",
        "fn": 86,
        "include_baseline_error": false,
        "n": 90,
        "reviewed": true,
        "value": 0.2008604570183643
    },
    "H2": {
        "error": 0.11829753285057355,
        "fit": "average_SEM",
        "value": -0.033985858606886014
    },
    "L1": {
        "error": 0.02741352536170133,
        "filter_outliers_dict": {
            "filter_outliers": true,
            "iterations": 1,
            "std_devs": 2
        },
        "fit": "Average",
        "fn": 90,
        "include_baseline_error": false,
        "n": 90,
        "reviewed": true,
        "value": 0.10110655024440753
    },
    "L2": {
        "error": 0.0037431085197912315,
        "filter_outliers_dict": {
            "filter_outliers": true,
            "iterations": 1,
            "std_devs": 2
        },
        "fit": "Average",
        "fn": 85,
        "include_baseline_error": false,
        "n": 90,
        "reviewed": true,
        "value": 0.14709097883280586
    }
}