{
    "AX": {
        "error": 0.05287275880219532, 
        "fit": "average_SEM", 
        "value": 0.004229701660854819
    }, 
    "CDD": {
        "error": 0.00017238342498841533, 
        "fit": "average_SEM", 
        "value": 0.00019354091540056592
    }, 
    "H1": {
        "error": 0.12411239137830264, 
        "fit": "average_SEM", 
        "value": -0.061649709710642736
    }, 
    "H2": {
        "error": 0.12058521785032858, 
        "fit": "average_SEM", 
        "value": -0.0644086964331412
    }, 
    "L1": {
        "error": 0.10832600786002682, 
        "fit": "average_SEM", 
        "value": -0.11896941027468226
    }, 
    "L2": {
        "error": 0.2691488778189047, 
        "fit": "average_SEM", 
        "value": 0.2976955713442294
    }
}