{
    "AX": {
        "error": 0.055459792766759934, 
        "fit": "average_SEM", 
        "value": 0.0016937026914092713
    }, 
    "CDD": {
        "error": 0.00010837509868514867, 
        "fit": "average_SEM", 
        "value": 8.149091154336929e-05
    }, 
    "H1": {
        "error": 0.11692820144295077, 
        "fit": "average_SEM", 
        "value": -0.21818615354908008
    }, 
    "H2": {
        "error": 0.11474511351538536, 
        "fit": "average_SEM", 
        "value": -0.17104708344559186
    }, 
    "L1": {
        "error": 0.12578568906856852, 
        "fit": "average_SEM", 
        "value": -0.2145742325442067
    }, 
    "L2": {
        "error": 0.23384214834961836, 
        "fit": "average_SEM", 
        "value": 0.10829694493440911
    }
}