{
    "AX": {
        "error": 0.055533615866385874, 
        "fit": "average_SEM", 
        "value": -0.0069985779603788005
    }, 
    "CDD": {
        "error": 6.157390799676494e-05, 
        "fit": "average_SEM", 
        "value": 2.673920535016805e-05
    }, 
    "H1": {
        "error": 0.11983123765090091, 
        "fit": "average_SEM", 
        "value": 0.25892913005372975
    }, 
    "H2": {
        "error": 0.10744809000335827, 
        "fit": "average_SEM", 
        "value": 0.18773720609533484
    }, 
    "L1": {
        "error": 0.0955997987342437, 
        "fit": "average_SEM", 
        "value": 0.128230789132067
    }, 
    "L2": {
        "error": 0.19783124043477088, 
        "fit": "average_SEM", 
        "value": 0.5204279476776719
    }
}