{
    "Ar36": {
        "error": 0.00014497136746922124, 
        "filter_outliers": true, 
        "fit": "Parabolic", 
        "fn": 572, 
        "include_baseline_error": false, 
        "iterations": 1, 
        "n": 600, 
        "std_devs": 2, 
        "value": 0.006799984645198375
    }, 
    "Ar37": {
        "error": 0.001703025975302294, 
        "filter_outliers": true, 
        "fit": "Linear", 
        "fn": 577, 
        "include_baseline_error": false, 
        "iterations": 1, 
        "n": 600, 
        "std_devs": 2, 
        "value": 0.10783140096196628
    }, 
    "Ar38": {
        "error": 0.0039289024687173555, 
        "filter_outliers": true, 
        "fit": "Linear", 
        "fn": 573, 
        "include_baseline_error": false, 
        "iterations": 1, 
        "n": 600, 
        "std_devs": 2, 
        "value": 0.9384007490164956
    }, 
    "Ar39": {
        "error": 0.011026264019905753, 
        "filter_outliers": true, 
        "fit": "Parabolic", 
        "fn": 579, 
        "include_baseline_error": false, 
        "iterations": 1, 
        "n": 600, 
        "std_devs": 2, 
        "value": 60.0088507110331
    }, 
    "Ar40": {
        "error": 0.007302467422564127, 
        "filter_outliers": true, 
        "fit": "Parabolic", 
        "fn": 574, 
        "include_baseline_error": false, 
        "iterations": 1, 
        "n": 600, 
        "std_devs": 2, 
        "value": 21.872778119332743
    }, 
    "Ar41": {
        "error": 0.0019809932147768646, 
        "filter_outliers": true, 
        "fit": "Average", 
        "fn": 569, 
        "include_baseline_error": false, 
        "iterations": 1, 
        "n": 600, 
        "std_devs": 2, 
        "value": 0.07917237980500319
    }, 
    "reviewed": true
}