{
    "Ar36": {
        "error": 0.0002670000349928606,
        "filter_outliers_dict": {
            "filter_outliers": true,
            "iterations": 1,
            "std_devs": 2
        },
        "fit": "Parabolic",
        "fn": 574,
        "include_baseline_error": false,
        "n": 600,
        "reviewed": true,
        "value": 0.031742493437632364
    },
    "Ar37": {
        "error": 0.0016641995147142511,
        "filter_outliers_dict": {
            "filter_outliers": true,
            "iterations": 1,
            "std_devs": 2
        },
        "fit": "Linear",
        "fn": 574,
        "include_baseline_error": false,
        "n": 600,
        "reviewed": true,
        "value": 0.041285925842333454
    },
    "Ar38": {
        "error": 0.0037807935541625975,
        "filter_outliers_dict": {
            "filter_outliers": true,
            "iterations": 1,
            "std_devs": 2
        },
        "fit": "Linear",
        "fn": 570,
        "include_baseline_error": false,
        "n": 600,
        "reviewed": true,
        "value": 0.33664904264597834
    },
    "Ar39": {
        "error": 0.007918721805616355,
        "filter_outliers_dict": {
            "filter_outliers": true,
            "iterations": 1,
            "std_devs": 2
        },
        "fit": "Parabolic",
        "fn": 578,
        "include_baseline_error": false,
        "n": 600,
        "reviewed": true,
        "value": 11.849417019317006
    },
    "Ar40": {
        "error": 0.008421106532958272,
        "filter_outliers_dict": {
            "filter_outliers": true,
            "iterations": 1,
            "std_devs": 2
        },
        "fit": "Parabolic",
        "fn": 573,
        "include_baseline_error": false,
        "n": 600,
        "reviewed": true,
        "value": 13.495593317293327
    },
    "Ar41": {
        "error": 0.04699880021874324,
        "fit": "linear",
        "value": 0.0723013088978544
    }
}