{
    "Ar36": {
        "error": 0.00014085439431486677,
        "filter_outliers_dict": {
            "filter_outliers": true,
            "iterations": 1,
            "std_devs": 2
        },
        "fit": "Parabolic",
        "fn": 570,
        "include_baseline_error": false,
        "n": 600,
        "reviewed": true,
        "value": 0.006442399185986342
    },
    "Ar37": {
        "error": 0.0016069117769429485,
        "filter_outliers_dict": {
            "filter_outliers": true,
            "iterations": 1,
            "std_devs": 2
        },
        "fit": "Linear",
        "fn": 571,
        "include_baseline_error": false,
        "n": 600,
        "reviewed": true,
        "value": 0.0648598062886459
    },
    "Ar38": {
        "error": 0.004049383627524342,
        "filter_outliers_dict": {
            "filter_outliers": true,
            "iterations": 1,
            "std_devs": 2
        },
        "fit": "Linear",
        "fn": 574,
        "include_baseline_error": false,
        "n": 600,
        "reviewed": true,
        "value": 0.878155323724825
    },
    "Ar39": {
        "error": 0.00999341075247135,
        "filter_outliers_dict": {
            "filter_outliers": true,
            "iterations": 1,
            "std_devs": 2
        },
        "fit": "Parabolic",
        "fn": 569,
        "include_baseline_error": false,
        "n": 600,
        "reviewed": true,
        "value": 58.511026129516466
    },
    "Ar40": {
        "error": 0.00711990736611645,
        "filter_outliers_dict": {
            "filter_outliers": true,
            "iterations": 1,
            "std_devs": 2
        },
        "fit": "Parabolic",
        "fn": 575,
        "include_baseline_error": false,
        "n": 600,
        "reviewed": true,
        "value": 20.950945609849782
    },
    "Ar41": {
        "error": 0.051135407484787634,
        "fit": "linear",
        "value": 0.06947242941203775
    }
}