{
    "Ar36": {
        "error": 0.027710512125571966, 
        "fit": "parabolic", 
        "value": 4.024104810156655
    }, 
    "Ar37": {
        "error": 0.20700906261149057, 
        "fit": "linear", 
        "value": 0.5141708478263165
    }, 
    "Ar38": {
        "error": 0.11154371397700791, 
        "fit": "linear", 
        "value": 1.0085145734014771
    }, 
    "Ar39": {
        "error": 0.058824599582231143, 
        "fit": "parabolic", 
        "value": 0.016919008045986974
    }, 
    "Ar40": {
        "error": 0.42628687367805512, 
        "fit": "parabolic", 
        "value": 1212.371958911122
    }, 
    "Ar41": {
        "error": 0.10701151564740058, 
        "fit": "average_SEM", 
        "value": 0.31568887349450958
    }
}