{
    "Ar36": {
        "error": 0.023794174621998412, 
        "fit": "parabolic", 
        "value": 4.1218426886759536
    }, 
    "Ar37": {
        "error": 0.27436736648878413, 
        "fit": "linear", 
        "value": 0.083762677722072632
    }, 
    "Ar38": {
        "error": 0.11277125541752969, 
        "fit": "linear", 
        "value": 0.5769947480930635
    }, 
    "Ar39": {
        "error": 0.056414878461864715, 
        "fit": "parabolic", 
        "value": 0.039148561953218419
    }, 
    "Ar40": {
        "error": 0.43632905052365017, 
        "fit": "parabolic", 
        "value": 1243.5524903648929
    }, 
    "Ar41": {
        "error": 0.11392772414947744, 
        "fit": "average_SEM", 
        "value": -0.14956068379022328
    }
}