{
    "Ar36": {
        "error": 0.00016261689983278706,
        "filter_outliers_dict": {
            "filter_outliers": true,
            "iterations": 1,
            "std_devs": 2
        },
        "fit": "Linear",
        "fn": 174,
        "include_baseline_error": false,
        "n": 180,
        "reviewed": true,
        "value": 0.0046570171232186795
    },
    "Ar37": {
        "error": 0.007462568694310345,
        "filter_outliers_dict": {
            "filter_outliers": true,
            "iterations": 1,
            "std_devs": 2
        },
        "fit": "Linear",
        "fn": 173,
        "include_baseline_error": false,
        "n": 180,
        "reviewed": true,
        "value": 0.15108475357077028
    },
    "Ar38": {
        "error": 0.03260801596261388,
        "filter_outliers_dict": {
            "filter_outliers": true,
            "iterations": 1,
            "std_devs": 2
        },
        "fit": "Linear",
        "fn": 175,
        "include_baseline_error": false,
        "n": 180,
        "reviewed": true,
        "value": 0.08985632209341401
    },
    "Ar39": {
        "error": 0.0024282045165678876,
        "filter_outliers_dict": {
            "filter_outliers": true,
            "iterations": 1,
            "std_devs": 2
        },
        "fit": "Linear",
        "fn": 173,
        "include_baseline_error": false,
        "n": 180,
        "reviewed": true,
        "value": 0.06869027431500054
    },
    "Ar40": {
        "error": 0.023982503297335228,
        "filter_outliers_dict": {
            "filter_outliers": true,
            "iterations": 1,
            "std_devs": 2
        },
        "fit": "Linear",
        "fn": 173,
        "include_baseline_error": false,
        "n": 180,
        "reviewed": true,
        "value": 1.7807728951869253
    },
    "Ar41": {
        "error": 0.1159253963814254,
        "fit": "average_SEM",
        "value": -0.031354052375213035
    }
}