{
    "Ar36": {
        "error": 0.00013837424893813194,
        "filter_outliers_dict": {
            "filter_outliers": true,
            "iterations": 1,
            "std_devs": 2
        },
        "fit": "Linear",
        "fn": 175,
        "include_baseline_error": false,
        "n": 180,
        "reviewed": true,
        "value": 0.004426678348631094
    },
    "Ar37": {
        "error": 0.0064740792317623756,
        "filter_outliers_dict": {
            "filter_outliers": true,
            "iterations": 1,
            "std_devs": 2
        },
        "fit": "Linear",
        "fn": 175,
        "include_baseline_error": false,
        "n": 180,
        "reviewed": true,
        "value": 0.026534548149797242
    },
    "Ar38": {
        "error": 0.024587493752131654,
        "filter_outliers_dict": {
            "filter_outliers": true,
            "iterations": 1,
            "std_devs": 2
        },
        "fit": "Linear",
        "fn": 174,
        "include_baseline_error": false,
        "n": 180,
        "reviewed": true,
        "value": -0.057161080367974335
    },
    "Ar39": {
        "error": 0.0015000460298790408,
        "filter_outliers_dict": {
            "filter_outliers": true,
            "iterations": 1,
            "std_devs": 2
        },
        "fit": "Linear",
        "fn": 173,
        "include_baseline_error": false,
        "n": 180,
        "reviewed": true,
        "value": 0.041098791399946266
    },
    "Ar40": {
        "error": 0.0175852495357578,
        "filter_outliers_dict": {
            "filter_outliers": true,
            "iterations": 1,
            "std_devs": 2
        },
        "fit": "Linear",
        "fn": 175,
        "include_baseline_error": false,
        "n": 180,
        "reviewed": true,
        "value": 1.4153262730825127
    },
    "Ar41": {
        "error": 0.11303768907438172,
        "fit": "average_SEM",
        "value": -0.11929816554766148
    }
}