{
    "Ar36": {
        "error": 0.00013113741478695205, 
        "filter_outliers": true, 
        "fit": "Parabolic", 
        "fn": 569, 
        "include_baseline_error": false, 
        "iterations": 1, 
        "n": 600, 
        "std_devs": 2, 
        "value": 0.004711887069205443
    }, 
    "Ar37": {
        "error": 0.0017621364560773654, 
        "filter_outliers": true, 
        "fit": "Linear", 
        "fn": 575, 
        "include_baseline_error": false, 
        "iterations": 1, 
        "n": 600, 
        "std_devs": 2, 
        "value": 0.019595597093958514
    }, 
    "Ar38": {
        "error": 0.004019585029249817, 
        "filter_outliers": true, 
        "fit": "Linear", 
        "fn": 571, 
        "include_baseline_error": false, 
        "iterations": 1, 
        "n": 600, 
        "std_devs": 2, 
        "value": 0.17130898982417903
    }, 
    "Ar39": {
        "error": 0.006535339508238325, 
        "filter_outliers": true, 
        "fit": "Parabolic", 
        "fn": 576, 
        "include_baseline_error": false, 
        "iterations": 1, 
        "n": 600, 
        "std_devs": 2, 
        "value": 0.04677893181472033
    }, 
    "Ar40": {
        "error": 0.00555372745614014, 
        "filter_outliers": true, 
        "fit": "Parabolic", 
        "fn": 576, 
        "include_baseline_error": false, 
        "iterations": 1, 
        "n": 600, 
        "std_devs": 2, 
        "value": 1.214107161520043
    }, 
    "Ar41": {
        "error": 0.0020421759697348426, 
        "filter_outliers": true, 
        "fit": "Average", 
        "fn": 573, 
        "include_baseline_error": false, 
        "iterations": 1, 
        "n": 600, 
        "std_devs": 2, 
        "value": 0.07625872315569736
    }, 
    "reviewed": true
}