{
    "Ar36": {
        "error": 0.00010529392849128337,
        "filter_outliers_dict": {
            "filter_outliers": true,
            "iterations": 1,
            "std_devs": 2
        },
        "fit": "Parabolic",
        "fn": 375,
        "include_baseline_error": false,
        "n": 400,
        "reviewed": true,
        "value": 0.0011606001005147891
    },
    "Ar37": {
        "error": 0.0019861314798442606,
        "filter_outliers_dict": {
            "filter_outliers": true,
            "iterations": 1,
            "std_devs": 2
        },
        "fit": "Linear",
        "fn": 378,
        "include_baseline_error": false,
        "n": 400,
        "reviewed": true,
        "value": 0.02718388476951828
    },
    "Ar38": {
        "error": 0.004995240007199644,
        "filter_outliers_dict": {
            "filter_outliers": true,
            "iterations": 1,
            "std_devs": 2
        },
        "fit": "Linear",
        "fn": 381,
        "include_baseline_error": false,
        "n": 400,
        "reviewed": true,
        "value": 0.18840788045431864
    },
    "Ar39": {
        "error": 0.009273104173819536,
        "filter_outliers_dict": {
            "filter_outliers": true,
            "iterations": 1,
            "std_devs": 2
        },
        "fit": "Parabolic",
        "fn": 384,
        "include_baseline_error": false,
        "n": 400,
        "reviewed": true,
        "value": 0.03513387813167339
    },
    "Ar40": {
        "error": 0.006865187139299338,
        "filter_outliers_dict": {
            "filter_outliers": true,
            "iterations": 1,
            "std_devs": 2
        },
        "fit": "Parabolic",
        "fn": 383,
        "include_baseline_error": false,
        "n": 400,
        "reviewed": true,
        "value": 0.17761765212921277
    },
    "Ar41": {
        "error": 0.051399181193733046,
        "fit": "linear",
        "value": 0.09504897370210627
    }
}