{
    "aliquot": 2, 
    "analysis_type": "unknown", 
    "collection_version": "0.1:0.1", 
    "comment": "E:3 SC 2.93 mg yellow", 
    "commit": "a809e348543f9a6781ca95fe9659e96c2abadefc", 
    "detectors": {
        "AX": {
            "deflection": null, 
            "gain": null
        }, 
        "CDD": {
            "deflection": null, 
            "gain": null
        }, 
        "H1": {
            "deflection": null, 
            "gain": null
        }, 
        "H2": {
            "deflection": null, 
            "gain": null
        }, 
        "L1": {
            "deflection": null, 
            "gain": null
        }, 
        "L2": {
            "deflection": null, 
            "gain": null
        }
    }, 
    "extraction": "", 
    "identifier": "63457", 
    "increment": 2, 
    "irradiation": "NM-274", 
    "irradiation_level": "E", 
    "irradiation_position": 3, 
    "isotopes": {
        "Ar36": {
            "classification": null, 
            "classification_probability": 0, 
            "detector": "CDD"
        }, 
        "Ar37": {
            "classification": null, 
            "classification_probability": 0, 
            "detector": "L2"
        }, 
        "Ar38": {
            "classification": null, 
            "classification_probability": 0, 
            "detector": "L1"
        }, 
        "Ar39": {
            "classification": null, 
            "classification_probability": 0, 
            "detector": "AX"
        }, 
        "Ar40": {
            "classification": null, 
            "classification_probability": 0, 
            "detector": "H1"
        }, 
        "Ar41": {
            "classification": null, 
            "classification_probability": 0, 
            "detector": "H2"
        }
    }, 
    "mass_spectrometer": "jan", 
    "material": "coarse san", 
    "measurement": "", 
    "project": "Toba", 
    "queue_conditionals_name": "", 
    "repository_identifier": "Toba", 
    "sample": "SF-1", 
    "spec_sha": "63bdfa621e4e1990f6b1c8e455b6f6c457aa09ff", 
    "timestamp": "2015-02-25T08:18:23", 
    "username": "MHeizler", 
    "uuid": "7de03f75-44b1-40a3-8669-f5928aa9af43"
}