{
    "AX": {
        "error": 0.045128326971136334, 
        "fit": "average", 
        "value": 0.01740239751077667
    }, 
    "CDD": {
        "error": 4.160778069342612e-05, 
        "fit": "average", 
        "value": 1.251032153959386e-05
    }, 
    "H1": {
        "error": 0.040835885259665444, 
        "fit": "average", 
        "value": -0.049855900559785664
    }, 
    "H2": {
        "error": 0.04869083938541135, 
        "fit": "average", 
        "value": 0.07068898873498979
    }, 
    "L1": {
        "error": 0.04244058311602764, 
        "fit": "average", 
        "value": 0.18931669550158128
    }, 
    "L2": {
        "error": 0.020008731871987772, 
        "fit": "average", 
        "value": -0.0040796896174815
    }
}