{
    "AX": {
        "error": 0.05345579575665231, 
        "fit": "average", 
        "value": 0.020447950768210904
    }, 
    "CDD": {
        "error": 3.4483505670262656e-05, 
        "fit": "average", 
        "value": 8.34021435972924e-06
    }, 
    "H1": {
        "error": 0.037316562149633144, 
        "fit": "average", 
        "value": -0.0430849764155402
    }, 
    "H2": {
        "error": 0.04839760935940333, 
        "fit": "average", 
        "value": 0.05578343643931074
    }, 
    "L1": {
        "error": 0.0431711359774667, 
        "fit": "average", 
        "value": 0.15324305392108684
    }, 
    "L2": {
        "error": 0.019358571925231688, 
        "fit": "average", 
        "value": -0.045983161981737415
    }
}